canadapostwrapper/__init__.py
canadapostwrapper/canadapost.py
canadapostwrapper-0.4.2.dist-info/LICENSE
canadapostwrapper-0.4.2.dist-info/METADATA
canadapostwrapper-0.4.2.dist-info/WHEEL
canadapostwrapper-0.4.2.dist-info/top_level.txt
canadapostwrapper-0.4.2.dist-info/RECORD
