Metadata-Version: 2.1
Name: canadapostwrapper
Version: 0.4.2
Summary: A wrapper for tracking packages with Canada Post
Home-page: https://github.com/shibakek2/canada-post
Author: shibakek
Author-email: wilhemnorman732@gmail.com
Classifier: Programming Language :: Python :: 3
Classifier: License :: OSI Approved :: MIT License
Classifier: Operating System :: OS Independent
Requires-Python: >=3.6
License-File: LICENSE
Requires-Dist: requests
